langgraph_a2a_server/__init__.py
langgraph_a2a_server/executor.py
langgraph_a2a_server/server.py
langgraph_a2a_server-0.1.6.dist-info/METADATA
langgraph_a2a_server-0.1.6.dist-info/WHEEL
langgraph_a2a_server-0.1.6.dist-info/licenses/LICENSE
langgraph_a2a_server-0.1.6.dist-info/RECORD
