Metadata-Version: 2.4
Name: langgraph-a2a-server
Version: 0.1.6
Summary: A2A Server implementation for LangGraph agents
Project-URL: Repository, https://github.com/5enxia/langgraph-a2a-server
License-File: LICENSE
Requires-Python: >=3.10
Requires-Dist: a2a-sdk[http-server]>=0.3.7
Requires-Dist: fastapi>=0.100.0
Requires-Dist: langgraph>=0.2.0
Requires-Dist: starlette>=0.27.0
Requires-Dist: uvicorn>=0.23.0
Provides-Extra: examples
Requires-Dist: langchain-core>=0.1.0; extra == 'examples'
Requires-Dist: langchain-openai>=0.0.5; extra == 'examples'
